lg/__init__.py
lg/api.py
lg/auth.py
lg/exceptions.py
lg/models/__init__.py
lg/models/commands.py
lg/models/gateway.py
lg/models/slc.py
lg/models/switch.py
tests/__init__.py
tests/lg/__init__.py
tests/lg/conftest.py
tests/lg/test_api.py
tests/lg/test_auth.py
ciberc_lg-0.7.1.dist-info/LICENSE.txt
ciberc_lg-0.7.1.dist-info/METADATA
ciberc_lg-0.7.1.dist-info/WHEEL
ciberc_lg-0.7.1.dist-info/top_level.txt
ciberc_lg-0.7.1.dist-info/RECORD
