Metadata-Version: 2.1
Name: ciberc-lg
Version: 0.7.1
Summary: Lighting Gale client
Author: CiberC Dev
License: GPLv3
Classifier: Topic :: Software Development :: Libraries :: Python Modules
Classifier: Programming Language :: Python :: 3.9
Classifier: Programming Language :: Python :: 3.10
Classifier: Programming Language :: Python :: 3.11
Requires-Python: >=3.9
License-File: LICENSE.txt
Requires-Dist: requests >=2.28
Requires-Dist: pydantic >=1.9
